easycore/__init__.py
easycore/common/__init__.py
easycore/common/config/__init__.py
easycore/common/config/config.py
easycore/common/config/hierarchical_config.py
easycore/common/network/__init__.py
easycore/common/network/download.py
easycore/common/parallel/__init__.py
easycore/common/parallel/engine.py
easycore/common/path/__init__.py
easycore/common/path/http_path_handler.py
easycore/common/path/path_handler.py
easycore/common/path/path_manager.py
easycore/common/path/redirect_path_handler.py
easycore/common/path/utils.py
easycore/common/registry/__init__.py
easycore/common/registry/registry.py
easycore/torch/__init__.py
easycore/torch/parallel/__init__.py
easycore/torch/parallel/engine.py
easycore-0.4.2.dist-info/LICENSE
easycore-0.4.2.dist-info/METADATA
easycore-0.4.2.dist-info/WHEEL
easycore-0.4.2.dist-info/top_level.txt
easycore-0.4.2.dist-info/RECORD
