Metadata-Version: 2.1
Name: easycore
Version: 0.4.2
Summary: a collection of tools to support research and development.
Home-page: https://github.com/YuxinZhaozyx/easycore
Author: Yuxin Zhao
License: LICENSE
Platform: UNKNOWN
Requires-Dist: pyyaml
Requires-Dist: tqdm
Requires-Dist: portalocker (>=1.6.0)
